stop/__init__.py
stop/canvas_object.py
stop/events.py
stop/favicon.ico
stop/project.py
stop/scratch_math.py
stop/scratch_time.py
stop/sensing.py
stop/sprite.py
stop/sprite_code.py
stop/assets/costume1.png
stop/assets/costume2.png
stop/convert/__init__.py
stop/convert/block.py
stop/convert/conversion_tables.py
stop/convert/convert.py
stop/convert/extract_files.py
stop/convert/main.py
stop/convert/prefs.py
stop/convert/scripts.py
stop/convert/sprite.py
stop-0.0.12.dist-info/LICENSE.txt
stop-0.0.12.dist-info/METADATA
stop-0.0.12.dist-info/WHEEL
stop-0.0.12.dist-info/top_level.txt
stop-0.0.12.dist-info/RECORD
