Metadata-Version: 2.1
Name: stop
Version: 0.0.12
Summary: Scratch to Python converter and creator
Home-page: https://github.com/dantechguy/stop
Author: Daniel Wendon-Blixrud
Author-email: d@nielwb.com
License: UNKNOWN
Platform: UNKNOWN
Classifier: Programming Language :: Python :: 3
Classifier: License :: OSI Approved :: MIT License
Classifier: Operating System :: OS Independent
